Workbook

Sheet Combine
B2: Paint Booth + Exhaust blower + Electrical control panel | C2: 1 | D2: Unit | E2: ='Costing Sheet'!I38 -> 649264 | F2: =E2*1.4 -> 908969.6 | G2: 0.4 | H2: =F2*0.1 -> 90896.96 | I2: Discount | J2: 0.05
B3: Exhaust Duct | C3: 1 | D3: Unit | E3: ='Costing Sheet'!I43 -> 105000 | F3: =E3*1.26 -> 132300 | G3: 0.25
B4: Dsign & Contingency | C4: 1 | D4: Unit | F4: 25000 | G4: 0
B5: Packing & Forwarding - Internal | C5: 1 | D5: Unit | F5: 11000 | G5: 0
B6: E & C | C6: 1 | D6: Unit | F6: 65000 | G6: 0
B7: Transport | C7: 1 | D7: Unit | E7: Customer scope
E8: =E2+E3 -> 754264 | F8: =SUM(F2:F7) -> 1142269.6 | G8: =F8-E8 -> 388005.6 | H8: Difference
H10: =G8-H2 -> 297108.64 | I10: Profit | J10: 0.27
F12: Final Price | H12: =F8-H2 -> 1051372.6

Sheet Costing Sheet
A1: VITECH ENVIRO SYTEMS PVT LTD
A4: CUSTOMER NAME : M/s | I4: Date : 24.07.2026
A5: S.NO | B5: DESCRIPTION | C5: RATING/SIZE | D5: QTY | E5: UNIT | F5: UNIT COST | G5: RM COST | H5: LABOUR COST | I5: TOTAL PRICE
A6: Non Pressurised - Enclosed Dry type Paint Booth Size - 3.0 W x 2.4.0 W x 2.4 H - Side Draft - (10' L x 8'W x 7'H)
B7: Materials
A8: 1 | B8: MS 18 SWG Sheet | C8: 2500 x 900 x 1.2 thk | D8: ='Paint Spray Booth - Dry'!E15 -> 621 | E8: Kgs | F8: 85 | G8: =ROUNDUP(D8*F8,0) -> 52785 | H8: =ROUNDUP(D8*45,0) -> 27945 | I8: =ROUNDUP(G8+H8,0) -> 80730
A9: 2 | B9: MS 14 SWG Sheet | C9: 2500 x 1250 x 2 thk | D9: ='Paint Spray Booth - Dry'!E19 -> 100 | E9: Kgs | F9: =F8 -> 85 | G9: =ROUNDUP(D9*F9,0) -> 8500 | H9: =ROUNDUP(D9*45,0) -> 4500 | I9: =ROUNDUP(G9+H9,0) -> 13000
A10: 3 | B10: MS Plate | C10: 2500 x 1250 x 6 thk | D10: ='Paint Spray Booth - Dry'!E17 -> 150 | E10: Kgs | F10: =F8 -> 85 | G10: =ROUNDUP(D10*F10,0) -> 12750 | H10: =ROUNDUP(D10*45,0) -> 6750 | I10: =ROUNDUP(G10+H10,0) -> 19500
A11: 4 | B11: MS Sq. Tube | C11: 40 x 40 x 2 thk x 6000 | D11: ='Paint Spray Booth - Dry'!G21 -> 126 | E11: Kgs | F11: 75 | G11: =ROUNDUP(D11*F11,0) -> 9450 | H11: =ROUNDUP(D11*50,0) -> 6300 | I11: =ROUNDUP(G11+H11,0) -> 15750
A12: 5 | B12: MS Channel | C12: 75 x 40 x 6 thk x 6000 | D12: ='Paint Spray Booth - Dry'!G23 -> 308 | E12: Kgs | F12: =F11 -> 75 | G12: =ROUNDUP(D12*F12,0) -> 23100 | H12: =ROUNDUP(D12*50,0) -> 15400 | I12: =ROUNDUP(G12+H12,0) -> 38500
A13: 6 | B13: MS Flat | C13: 40 x 6 thk x 6000 | D13: ='Paint Spray Booth - Dry'!G25 -> 12 | E13: Kgs | F13: =F11 -> 75 | G13: =ROUNDUP(D13*F13,0) -> 900 | H13: =ROUNDUP(D13*50,0) -> 600 | I13: =ROUNDUP(G13+H13,0) -> 1500
A14: 7 | B14: MS Wire mesh | C14: Dia 3 x 25 Sq. | D14: =3*2.1*11*1.1 -> 76.23 | E14: Sq. ft | F14: 75 | G14: =ROUNDUP(D14*F14,0) -> 5718 | I14: =ROUNDUP(G14+H14,0) -> 5718
B15: Bought Out Items
A16: 8 | B16: LED Light | C16: NFLP - 90 W ~ 800 lux | D16: 4 | E16: Nos | F16: 9500 | G16: =F16*D16 -> 38000 | I16: =ROUNDUP(G16+H16,0) -> 38000
A17: 9 | B17: Silicone Sealant | C17: 101 - 300 ml | D17: 10 | E17: Nos | F17: 350 | G17: =F17*D17 -> 3500 | I17: =ROUNDUP(G17+H17,0) -> 3500
A18: 10 | B18: GI Bolt, Nut & 2 Washer | C18: M8 x 20L | D18: 300 | E18: Nos | F18: 8 | G18: =F18*D18 -> 2400 | I18: =ROUNDUP(G18+H18,0) -> 2400
A19: 11 | B19: GI Bolt, Nut & 2 Washer | C19: M8 x 25 L | D19: 300 | E19: Nos | F19: 10 | G19: =F19*D19 -> 3000 | I19: =ROUNDUP(G19+H19,0) -> 3000
A20: 12 | B20: GI Bolt, Nut & 2 Washer | C20: M8 x 60 L | D20: 250 | E20: Nos | F20: 15 | G20: =F20*D20 -> 3750 | I20: =ROUNDUP(G20+H20,0) -> 3750
A21: 13 | B21: GI Bolt, Nut & 2 Washer | C21: M10 x 50 L | D21: 50 | E21: Nos | F21: 20 | G21: =F21*D21 -> 1000 | I21: =ROUNDUP(G21+H21,0) -> 1000
A22: 14 | B22: Rubber Gasket | C22: Blower | D22: 1 | E22: nos | F22: 2500 | G22: =F22*D22 -> 2500 | I22: =ROUNDUP(G22+H22,0) -> 2500
A23: 15 | B23: Paint arrest paper filter | D23: =3*2.1*1.1 -> 6.93 | E23: Sq. m | F23: 350 | G23: =F23*D23 -> 2425.5 | I23: =ROUNDUP(G23+H23,0) -> 2426
A24: 16 | B24: Air inlet filters (Box) | C24: 610 x 610 x 30 | D24: 8 | E24: Nos | F24: 950 | G24: =F24*D24 -> 7600 | I24: =ROUNDUP(G24+H24,0) -> 7600
A25: 17 | B25: View Glass | C25: 450 x 450 x 5 with rubber beading | D25: 8 | E25: Nos | F25: 3000 | G25: =F25*D25 -> 24000 | I25: =ROUNDUP(G25+H25,0) -> 24000
A26: 18 | B26: Top track | C26: Dia 20 MS Rod & 75 x 6 MS Flat - 6 m L | D26: 1 | E26: Nos | F26: 3000 | G26: =F26*D26 -> 3000 | I26: =ROUNDUP(G26+H26,0) -> 3000
A27: 19 | B27: Top roller | D27: 4 | E27: Nos | F27: 1000 | G27: =F27*D27 -> 4000 | I27: =ROUNDUP(G27+H27,0) -> 4000
A28: 20 | B28: Bottom track | C28: STD - 3m L | D28: 1 | E28: Nos | F28: 7500 | G28: =F28*D28 -> 7500 | I28: =ROUNDUP(G28+H28,0) -> 7500
A29: 21 | B29: Bottom wheel | D29: 4 | E29: Nos | F29: 1000 | G29: =F29*D29 -> 4000 | I29: =ROUNDUP(G29+H29,0) -> 4000
A30: 22 | B30: Door Handle | D30: 8 | E30: set | F30: 900 | G30: =F30*D30 -> 7200 | I30: =ROUNDUP(G30+H30,0) -> 7200
A31: 23 | B31: Black Handle | C31: 120 - P | D31: 4 | E31: Nos | F31: 250 | G31: =F31*D31 -> 1000 | I31: =ROUNDUP(G31+H31,0) -> 1000
A32: 24 | B32: Blower | C32: CLP-4" WC-10 HP-9000Cfm-Direct Drive | D32: 1 | E32: Nos | F32: 65000 | G32: =F32*D32 -> 65000 | I32: =ROUNDUP(G32+H32,0) -> 65000
A33: 25 | B33: Motor - CG | C33: 10HP, 1440 rpm - NFLP - Flange, IE2 | D33: 1 | E33: Nos | F33: 35000 | G33: =F33*D33 -> 35000 | I33: =ROUNDUP(G33+H33,0) -> 35000
A34: 26 | B34: Manual Sliding Door accessories | C34: 2000 x 2350 - Double leaf | D34: 1 | E34: Nos | F34: 10000 | G34: =F34*D34 -> 10000 | I34: =ROUNDUP(G34+H34,0) -> 10000
A35: 27 | B35: Electrical Control panel | C35: 10 HP Blower - 1nos ON/OFF & LED Light 4 nos with star delta | D35: 1 | E35: lot | F35: 95000 | G35: =F35*D35 -> 95000 | I35: =ROUNDUP(G35+H35,0) -> 95000
A36: 28 | B36: Filed wiring | C36: 10 HP Blower - 1nos ON/OFF & LED Light 4 nos with star delta | D36: 1 | E36: lot | F36: 115000 | G36: =F36*D36 -> 115000 | I36: =ROUNDUP(G36+H36,0) -> 115000
A37: 29 | B37: Painting | D37: ='Paint Spray Booth - Dry'!C30 -> 1134 | E37: Sq.ft | F37: 35 | G37: =D37*F37 -> 39690 | I37: =G37 -> 39690
A38: Paint Spray Booth Total Cost | I38: =SUM(I8:I37) -> 649264
A40: GI Exhaust Duct
A41: 1 | B41: GI Duct | C41: 600 x 600 x 10 Mtrs | D41: =0.6*4*10*1.1 -> 26.4 | E41: Sq.mtrs | F41: 3500 | G41: =ROUNDUP(D41*F41,0) -> 92400 | I41: =ROUNDUP(G41+H41,0) -> 92400
A42: 2 | B42: MS Support | D42: =4*21 -> 84 | E42: kgs | F42: 150 | G42: =D42*F42 -> 12600 | I42: =G42 -> 12600
A43: GI Exhaust Duct Total Cost | I43: =SUM(I40:I42) -> 105000

Sheet Paint Spray Booth - Dry
B2: Paint Spray Booth - Dry Type | C2: Size | E2: L | F2: W | G2: H
C3: Working | E3: 3000 | F3: 2250 | G3: 2400
C5: Outer | E5: =E3+100 -> 3100 | F5: =F3+750 -> 3000 | G5: =G3+100+50 -> 2550 | K5: =E3 -> 3000 | L5: =G3 -> 2400
B6: 900 x 2500 x 1.2 thk MS Sheet
B7: Booth | L7: =(K5/1000)*(L5/1000) -> 7.2 | M7: m2
B8: Back | C8: =ROUNDUP((E5/750)*(G3/2500),0) -> 4 | D8: nos | L8: 0.5 | M8: m/sec
B9: front | C9: =C8 -> 4 | D9: nos | L9: =L7*L8*3600 -> 12960 | M9: CMH
B10: Right | C10: =ROUNDUP(F5/750*(G3/2500),0) -> 4 | D10: nos
B11: Left | C11: =C10 -> 4 | D11: nos | L11: =L9/1.7 -> 7623.5294 | M11: cfm
B12: Top | C12: =ROUNDUP((E5/750)*(F5/2500),0) -> 5 | D12: nos
B13: Filter frame top & Bottom | C13: 4 | D13: nos | L13: CLP -4-10-9000
B14: Service Door | C14: 2 | D14: nos
C15: =SUM(C8:C14) -> 27 | D15: nos | E15: =C15*23 -> 621 | F15: kgs | G15: =ROUNDUP(C15*3.2+(C15*3.25*10%),0) -> 96 | H15: Sq.mtr
B17: 1250 x 2500 x 6 thk MS Plate Blower Mounting | C17: 1 | D17: nos | E17: =C17*150 -> 150 | F17: kgs
B19: 1250 x 2500 x 2 thk 14 swg MS Sheet Filter frame | C19: 2 | D19: nos | E19: =C19*50 -> 100 | F19: kgs
B21: MS Sq. Tube - 40 x 40 3 x 6000 | C21: =ROUNDUP(((E5/1000)*3)+((F5/1000)*2)+((1000/1000)*4)+((1500/1000)*4)+((2450/1000)*4),0) -> 36 | D21: mtrs | E21: =ROUNDUP(C21/6,0) -> 6 | F21: nos | G21: =E21*21 -> 126 | H21: kgs
B23: MS Channel - 75 x 40 x 6 x 6000 | C23: =ROUNDUP(((E5/1000)*3)+((F5/1000)*2)+((G5/1000)*8)+((1000/1000)*4),0) -> 40 | D23: mtrs | E23: =ROUNDUP(C23/6,0) -> 7 | F23: nos | G23: =E23*44 -> 308 | H23: Kgs
B25: MS Flat 40 x 6 x 6000 | C25: 6 | D25: mtrs | E25: =ROUNDUP(C25/6,0) -> 1 | F25: nos | G25: =E25*12 -> 12 | H25: kgs
B27: Painting
C28: =ROUNDUP((C17+C15+C19)*3.25*10.76,0) -> 1050 | D28: Sq. ft
B29: Stucture Materials | C29: =(E21+E25+E23)*6*0.25*4 -> 84 | D29: Sq. ft
C30: =SUM(C28:C29) -> 1134 | D30: Sq. ft
